sorting_visualizer/__init__.py
sorting_visualizer/sort.py
sorting_visualizer/variables.py
sorting_visualizer/visualizer.py
sorting_visualizer-1.0.dist-info/LICENSE
sorting_visualizer-1.0.dist-info/METADATA
sorting_visualizer-1.0.dist-info/WHEEL
sorting_visualizer-1.0.dist-info/top_level.txt
sorting_visualizer-1.0.dist-info/RECORD
