Metadata-Version: 2.1
Name: sorting-visualizer
Version: 1.0
Summary: A package to visualize various sorting algorithms.
Home-page: https://github.com/debdutgoswami/sorting-visualizer
Author: Debdut Goswami
Author-email: debdutgoswami@gmail.com
License: UNKNOWN
Download-URL: https://github.com/debdutgoswami/sorting-visualizer/archive/v1.0.tar.gz
Keywords: SORT,ALGORITHM,VISUALIZE
Platform: UNKNOWN
Classifier: Programming Language :: Python :: 3
Classifier: License :: OSI Approved :: MIT License
Classifier: Operating System :: OS Independent
Requires-Python: >=3.7
Requires-Dist: matplotlib
